nuclia.plone-1.0b1-py3.10-nspkg.pth
nuclia/plone/__init__.py
nuclia/plone/configure.zcml
nuclia/plone/events.py
nuclia/plone/interfaces.py
nuclia/plone/nuclia_api.py
nuclia/plone/permissions.zcml
nuclia/plone/settings.py
nuclia/plone/setuphandlers.py
nuclia/plone/testing.py
nuclia/plone/browser/__init__.py
nuclia/plone/browser/configure.zcml
nuclia/plone/browser/reindex.pt
nuclia/plone/browser/reindex.py
nuclia/plone/browser/search.pt
nuclia/plone/browser/search.py
nuclia/plone/locales/README.rst
nuclia/plone/locales/__init__.py
nuclia/plone/locales/nuclia.plone.pot
nuclia/plone/locales/update.py
nuclia/plone/locales/update.sh
nuclia/plone/locales/en/LC_MESSAGES/nuclia.plone.po
nuclia/plone/profiles/default/actions.xml
nuclia/plone/profiles/default/browserlayer.xml
nuclia/plone/profiles/default/catalog.xml
nuclia/plone/profiles/default/controlpanel.xml
nuclia/plone/profiles/default/metadata.xml
nuclia/plone/profiles/default/rolemap.xml
nuclia/plone/profiles/default/registry/main.xml
nuclia/plone/profiles/uninstall/browserlayer.xml
nuclia/plone/tests/__init__.py
nuclia/plone/tests/test_robot.py
nuclia/plone/tests/test_setup.py
nuclia/plone/tests/robot/test_example.robot
nuclia.plone-1.0b1.dist-info/LICENSE.GPL
nuclia.plone-1.0b1.dist-info/LICENSE.rst
nuclia.plone-1.0b1.dist-info/METADATA
nuclia.plone-1.0b1.dist-info/WHEEL
nuclia.plone-1.0b1.dist-info/entry_points.txt
nuclia.plone-1.0b1.dist-info/namespace_packages.txt
nuclia.plone-1.0b1.dist-info/top_level.txt
nuclia.plone-1.0b1.dist-info/RECORD
